lifegame/__about__.py
lifegame/__init__.py
lifegame/__main__.py
lifegame/biosquare.py
lifegame/genesis.py
lifegame/lensfilter.py
lifegame/screen.py
lifegame/term.py
lifegame/timer.py
lifegame/cli/__init__.py
lifegame_tui-0.2.0.dist-info/METADATA
lifegame_tui-0.2.0.dist-info/WHEEL
lifegame_tui-0.2.0.dist-info/entry_points.txt
lifegame_tui-0.2.0.dist-info/RECORD
