Metadata-Version: 2.1
Name: LifeGame-TUI
Version: 0.2.0
Summary: A simple implementation of the classic cellular automaton, Conway's Game of Life.
Project-URL: Source, https://github.com/Lingxuan-Ye/lifegame/tree/main/python
Author-email: Lingxuan Ye <love@lingxuan.io>
License-Expression: MIT
Classifier: Development Status :: 4 - Beta
Classifier: Programming Language :: Python
Classifier: Programming Language :: Python :: 3.10
Classifier: Programming Language :: Python :: 3.11
Requires-Python: >=3.10
Requires-Dist: click
Requires-Dist: numpy
Requires-Dist: scipy
